roboflow/__init__.py
roboflow/config.py
roboflow/archive/__init__.py
roboflow/archive/plot.py
roboflow/core/__init__.py
roboflow/core/model.py
roboflow/core/project.py
roboflow/core/version.py
roboflow/core/workspace.py
roboflow/models/__init__.py
roboflow/models/classification.py
roboflow/models/object_detection.py
roboflow/util/__init__.py
roboflow/util/image_utils.py
roboflow/util/prediction.py
roboflowtest-0.0.2.dist-info/LICENSE
roboflowtest-0.0.2.dist-info/METADATA
roboflowtest-0.0.2.dist-info/WHEEL
roboflowtest-0.0.2.dist-info/top_level.txt
roboflowtest-0.0.2.dist-info/RECORD
