Metadata-Version: 2.1
Name: roboflowtest
Version: 0.0.2
Summary: Ergonomic machine learning
Home-page: https://github.com/Palashio/libra
Author: Palash Shah
Author-email: ps9cmk@virginia.edu
License: UNKNOWN
Platform: UNKNOWN
Classifier: Programming Language :: Python :: 3
Classifier: License :: OSI Approved :: MIT License
Classifier: Operating System :: OS Independent
Requires-Python: >=3.6
License-File: LICENSE
Requires-Dist: certifi (==2021.5.30)
Requires-Dist: chardet (==4.0.0)
Requires-Dist: cycler (==0.10.0)
Requires-Dist: idna (==2.10)
Requires-Dist: kiwisolver (==1.3.1)
Requires-Dist: matplotlib
Requires-Dist: numpy (==1.19.5)
Requires-Dist: opencv-python (==4.5.3.56)
Requires-Dist: pillow
Requires-Dist: pyparsing (==2.4.7)
Requires-Dist: python-dateutil
Requires-Dist: python-dotenv
Requires-Dist: requests (==2.25.1)
Requires-Dist: six
Requires-Dist: urllib3 (==1.26.6)
